try_nbdev/__init__.py
try_nbdev/_nbdev.py
try_nbdev/core.py
try_nbdev/math_symbols.py
try_nbdev-0.0.1.dist-info/LICENSE
try_nbdev-0.0.1.dist-info/METADATA
try_nbdev-0.0.1.dist-info/WHEEL
try_nbdev-0.0.1.dist-info/entry_points.txt
try_nbdev-0.0.1.dist-info/top_level.txt
try_nbdev-0.0.1.dist-info/RECORD
