Metadata-Version: 2.1
Name: try-nbdev
Version: 0.0.1
Summary: My journey trying nbdev
Home-page: https://github.com/denilson/try_nbdev
Author: Denilson
Author-email: denilson020898@gmail.com
License: Apache Software License 2.0
Keywords: ipython nbdev pypi
Platform: UNKNOWN
Classifier: Development Status :: 3 - Alpha
Classifier: Intended Audience :: Developers
Classifier: License :: OSI Approved :: Apache Software License
Classifier: Natural Language :: English
Classifier: Programming Language :: Python :: 3.6
Classifier: Programming Language :: Python :: 3.7
Classifier: Programming Language :: Python :: 3.8
Requires-Python: >=3.6
